utils_tesis/__init__.py
utils_tesis/auxfunctions.py
utils_tesis/dataset_creator.py
utils_tesis/detection.py
utils_tesis/integration.py
utils_tesis/plot_api.py
utils_tesis/signalload.py
utils_tesis-0.1.4.dist-info/METADATA
utils_tesis-0.1.4.dist-info/WHEEL
utils_tesis-0.1.4.dist-info/licenses/LICENSE
utils_tesis-0.1.4.dist-info/RECORD
