Metadata-Version: 2.4
Name: utils_tesis
Version: 0.1.4
Summary: Auxiliar functions for my thesis
Author-email: alvarohc777 <aherrada@uninorte.edu.co>
License-File: LICENSE
Classifier: License :: OSI Approved :: MIT License
Classifier: Operating System :: OS Independent
Classifier: Programming Language :: Python :: 3
Requires-Python: >=3.7
